bleedfacedetector/__init__.py
bleedfacedetector/deploy.prototxt.txt
bleedfacedetector/fullapi.py
bleedfacedetector/haarcascade_frontalface_default.xml
bleedfacedetector/mmod_human_face_detector.dat
bleedfacedetector/res10_300x300_ssd_iter_140000.caffemodel
bleedfacedetector-1.0.17.dist-info/LICENSE
bleedfacedetector-1.0.17.dist-info/METADATA
bleedfacedetector-1.0.17.dist-info/WHEEL
bleedfacedetector-1.0.17.dist-info/top_level.txt
bleedfacedetector-1.0.17.dist-info/RECORD
