Metadata-Version: 2.1
Name: bleedfacedetector
Version: 1.0.17
Summary: A Python package that lets users use 4 different face detectors
Home-page: https://github.com/TahaAnwar/bleedfacedetector
Author: Taha Anwar
Author-email: taha@bleedai.com
License: BSD
Platform: UNKNOWN
Classifier: License :: OSI Approved :: BSD License
Classifier: Programming Language :: Python :: 3
Classifier: Programming Language :: Python :: 3.6
Classifier: Intended Audience :: Developers
Classifier: Topic :: Software Development :: Build Tools
Requires-Dist: numpy
